xai_evals/__init__.py
xai_evals/explainer.py
xai_evals/metrics.py
xai_evals/utils.py
xai_evals-0.0.12.dist-info/licenses/LICENSE
xai_evals-0.0.12.dist-info/METADATA
xai_evals-0.0.12.dist-info/WHEEL
xai_evals-0.0.12.dist-info/top_level.txt
xai_evals-0.0.12.dist-info/RECORD
