Metadata-Version: 2.4
Name: xai_evals
Version: 0.0.12
Summary: A package for model explainability and explainability comparision for tabular data
Home-page: https://github.com/AryaXAI/xai_evals
License: MIT
Keywords: aryaxai deep learning backtrace,ML observability
Classifier: Intended Audience :: Developers
Classifier: Intended Audience :: Science/Research
Classifier: Programming Language :: Python :: 3
Classifier: License :: OSI Approved :: MIT License
Classifier: Operating System :: OS Independent
Requires-Python: >=3.0
License-File: LICENSE
Requires-Dist: dl_backtrace
Requires-Dist: shap==0.46.0
Requires-Dist: lime==0.2.0.1
Requires-Dist: xgboost==2.1.3
Requires-Dist: scikit-learn==1.3.2
Requires-Dist: pandas==2.1.4
Requires-Dist: numpy==1.26.4
Requires-Dist: catboost==1.2.7
Requires-Dist: lightgbm==4.5.0
Requires-Dist: tensorflow==2.14.0
Requires-Dist: captum==0.7.0
Requires-Dist: quantus==0.5.3
Requires-Dist: tf-explain
Requires-Dist: torch
Requires-Dist: tqdm
Requires-Dist: opencv-python==4.11.0.86
Dynamic: classifier
Dynamic: description
Dynamic: description-content-type
Dynamic: home-page
Dynamic: keywords
Dynamic: license
Dynamic: license-file
Dynamic: requires-dist
Dynamic: requires-python
Dynamic: summary
